MANIFEST.in
README.md
setup.py
./opentc/__init__.py
./opentc/icap/__init__.py
./opentc/icap/server.py
./opentc/icap/setting.py
bin/opentc-icap
config/logging.yml
config/opentc-icap.yml
opentc_icap.egg-info/PKG-INFO
opentc_icap.egg-info/SOURCES.txt
opentc_icap.egg-info/dependency_links.txt
opentc_icap.egg-info/not-zip-safe
opentc_icap.egg-info/requires.txt
opentc_icap.egg-info/top_level.txt