Metadata-Version: 1.1
Name: opentc-icap
Version: 0.1.13
Summary: ICAP Server for OpenTC (A text classification engine using machine learning)
Home-page: https://github.com/cahya-wirawan/opentc-icap
Author: Cahya Wirawan
Author-email: Cahya.Wirawan@gmail.com
License: MIT
Keywords: machine learning cnn svm bayesian
Platform: UNKNOWN
Classifier: Development Status :: 3 - Alpha
Classifier: License :: OSI Approved :: MIT License
Classifier: Programming Language :: Python :: 3.5
Classifier: Topic :: Scientific/Engineering :: Artificial Intelligence
Classifier: Topic :: Text Processing :: Filters
